ing0.py
ing0_spawn-0.2.0.dist-info/LICENSE
ing0_spawn-0.2.0.dist-info/METADATA
ing0_spawn-0.2.0.dist-info/WHEEL
ing0_spawn-0.2.0.dist-info/entry_points.txt
ing0_spawn-0.2.0.dist-info/RECORD
