Metadata-Version: 2.1
Name: ing0-spawn
Version: 0.2.0
Summary: Build, test, and run your code on any GNU/Linux distribution with ease
License: CC0
Author: Amirouche Boubekki
Author-email: amirouche@hyper.dev
Requires-Python: >=3.9,<4.0
Classifier: License :: Other/Proprietary License
Classifier: Programming Language :: Python :: 3
Classifier: Programming Language :: Python :: 3.9
Classifier: Programming Language :: Python :: 3.10
Classifier: Programming Language :: Python :: 3.11
Requires-Dist: lxml (>=4.9.3,<5.0.0)
Requires-Dist: requests (>=2.31.0,<3.0.0)
